yta_math_interpolation/__init__.py
yta_math_interpolation/abstract.py
yta_math_interpolation/bezier_cubic.py
yta_math_interpolation/bezier_quadratic.py
yta_math_interpolation/curves/__init__.py
yta_math_interpolation/curves/enums.py
yta_math_interpolation/curves/parameters.py
yta_math_interpolation/curves/points_math.py
yta_math_interpolation/enums.py
yta_math_interpolation/linear.py
yta_math_interpolation-0.0.5.dist-info/licenses/LICENSE
yta_math_interpolation-0.0.5.dist-info/METADATA
yta_math_interpolation-0.0.5.dist-info/WHEEL
yta_math_interpolation-0.0.5.dist-info/RECORD
